async_client/__init__.py
async_client/_client.py
async_client/_exceptions.py
async_client/_settnigs.py
async_client_lib-0.1.9.dist-info/LICENSE
async_client_lib-0.1.9.dist-info/METADATA
async_client_lib-0.1.9.dist-info/WHEEL
async_client_lib-0.1.9.dist-info/RECORD
