Metadata-Version: 2.3
Name: async-client-lib
Version: 0.1.9
Summary: Asynchronous HTTP client
License: MIT
Author: Aleksey Matyunin
Author-email: matyunin.as@mail.ru
Requires-Python: >=3.9,<4.0
Classifier: License :: OSI Approved :: MIT License
Classifier: Programming Language :: Python :: 3
Classifier: Programming Language :: Python :: 3.9
Classifier: Programming Language :: Python :: 3.10
Classifier: Programming Language :: Python :: 3.11
Classifier: Programming Language :: Python :: 3.12
Classifier: Programming Language :: Python :: 3.13
Requires-Dist: aiohttp (>=3.8.4,<4.0.0)
Requires-Dist: backoff (>=2.2.1,<3.0.0)
Requires-Dist: pydantic (>=2.10.4,<3.0.0)
Requires-Dist: pydantic_settings (>=2.5.1,<3.0.0)
